MANIFEST.in
README.rst
setup.py
ddpclient/__init__.py
ddpclient/auth.py
ddpclient/client.py
ddpclient/operation.py
ddpclient/selector.py
ddpclient/soap_entity.py
ddpclient/user_list_client_selector.py
ddpclient/user_list_selector.py
ddpclient.egg-info/PKG-INFO
ddpclient.egg-info/SOURCES.txt
ddpclient.egg-info/dependency_links.txt
ddpclient.egg-info/entry_points.txt
ddpclient.egg-info/requires.txt
ddpclient.egg-info/top_level.txt