Metadata-Version: 1.1
Name: ddpclient
Version: 2.0.1
Summary: A client library for DDP API
Home-page: https://github.com/insiight/ddpclient
Author: David Lin
Author-email: david.lin@effectivemeasure.com
License: MIT
Keywords: DDP API client
Platform: UNKNOWN
Classifier: Development Status :: 3 - Alpha
Classifier: Intended Audience :: Developers
Classifier: Topic :: Software Development :: Libraries :: Python Modules
Classifier: License :: OSI Approved :: MIT License
Classifier: Programming Language :: Python :: 3.6
